xontrib/macro/__init__.py
xontrib/macro/data.py
xontrib/macro/docker.py
xontrib/macro/run.py
xontrib/macro/signal.py
xontrib_macro-0.4.2.dist-info/LICENSE
xontrib_macro-0.4.2.dist-info/METADATA
xontrib_macro-0.4.2.dist-info/WHEEL
xontrib_macro-0.4.2.dist-info/top_level.txt
xontrib_macro-0.4.2.dist-info/RECORD
