Metadata-Version: 2.1
Name: xontrib-macro
Version: 0.4.2
Summary: Library of the useful macroses for the xonsh shell.
Author-email: xontrib-macro <no@no.no>
License: MIT License
Project-URL: Homepage, https://github.com/anki-code/xontrib-macro
Project-URL: Documentation, https://github.com/anki-code/xontrib-macro/blob/master/README.md
Project-URL: Code, https://github.com/anki-code/xontrib-macro
Project-URL: Issue tracker, https://github.com/anki-code/xontrib-macro/issues
Platform: any
Classifier: Programming Language :: Python :: 3
Classifier: License :: OSI Approved :: MIT License
Classifier: Operating System :: OS Independent
Classifier: Topic :: System :: Shells
Classifier: Topic :: System :: System Shells
Classifier: Topic :: Terminals
Requires-Python: >=3.8
License-File: LICENSE
Requires-Dist: xonsh >=0.12.5
Provides-Extra: dev
Requires-Dist: pytest >=7.0 ; extra == 'dev'
